PyIF/CPU_TE.py
PyIF/GPU_TE.py
PyIF/__init__.py
PyIF/helper.py
PyIF/te_compute.py
PyIF-0.1.dist-info/METADATA
PyIF-0.1.dist-info/WHEEL
PyIF-0.1.dist-info/top_level.txt
PyIF-0.1.dist-info/RECORD
