Metadata-Version: 2.1
Name: PyIF
Version: 0.1
Summary: An open source implementation to compute bi-variate Transfer Entropy.
Home-page: https://github.com/lcdm-uiuc/PyTE
Author: Kelechi Ikegwu, Jacob Trauger, Robert Brunner
Author-email: ikegwu2@illinois.edu, jtt2@illinois.edu, bigdog@illinois.edu
License: UNKNOWN
Platform: UNKNOWN
Classifier: Programming Language :: Python :: 3
Classifier: License :: OSI Approved :: University of Illinois/NCSA Open Source License
Classifier: Operating System :: OS Independent
